yanwu/__init__.py
yanwu/app.py
yanwu-0.0.2.dist-info/LICENSE
yanwu-0.0.2.dist-info/METADATA
yanwu-0.0.2.dist-info/WHEEL
yanwu-0.0.2.dist-info/top_level.txt
yanwu-0.0.2.dist-info/RECORD
