Metadata-Version: 2.1
Name: yanwu
Version: 0.0.2
Summary: A tiny framework for python cli tools
Author-email: Richard Ma <richard.ma.19850509@gmail.com>
License: MIT License        
Project-URL: Homepage, https://github.com/richard-ma/yanwu
Project-URL: Bug Tracker, https://github.com/richard-ma/yanwu/issues
Classifier: Programming Language :: Python :: 3
Classifier: License :: OSI Approved :: MIT License
Classifier: Operating System :: OS Independent
Requires-Python: >=3.8
License-File: LICENSE
